alibabacloud_companyreg20200306/__init__.py
alibabacloud_companyreg20200306/client.py
alibabacloud_companyreg20200306/models/__init__.py
alibabacloud_companyreg20200306/models/_bind_produce_authorization_request.py
alibabacloud_companyreg20200306/models/_bind_produce_authorization_response.py
alibabacloud_companyreg20200306/models/_bind_produce_authorization_response_body.py
alibabacloud_companyreg20200306/models/_close_intention_for_partner_request.py
alibabacloud_companyreg20200306/models/_close_intention_for_partner_response.py
alibabacloud_companyreg20200306/models/_close_intention_for_partner_response_body.py
alibabacloud_companyreg20200306/models/_close_user_intention_request.py
alibabacloud_companyreg20200306/models/_close_user_intention_response.py
alibabacloud_companyreg20200306/models/_close_user_intention_response_body.py
alibabacloud_companyreg20200306/models/_create_business_opportunity_request.py
alibabacloud_companyreg20200306/models/_create_business_opportunity_response.py
alibabacloud_companyreg20200306/models/_create_business_opportunity_response_body.py
alibabacloud_companyreg20200306/models/_create_produce_for_partner_request.py
alibabacloud_companyreg20200306/models/_create_produce_for_partner_response.py
alibabacloud_companyreg20200306/models/_create_produce_for_partner_response_body.py
alibabacloud_companyreg20200306/models/_describe_partner_config_request.py
alibabacloud_companyreg20200306/models/_describe_partner_config_response.py
alibabacloud_companyreg20200306/models/_describe_partner_config_response_body.py
alibabacloud_companyreg20200306/models/_generate_upload_file_policy_request.py
alibabacloud_companyreg20200306/models/_generate_upload_file_policy_response.py
alibabacloud_companyreg20200306/models/_generate_upload_file_policy_response_body.py
alibabacloud_companyreg20200306/models/_get_alipay_url_request.py
alibabacloud_companyreg20200306/models/_get_alipay_url_response.py
alibabacloud_companyreg20200306-2.2.5.dist-info/LICENSE
alibabacloud_companyreg20200306-2.2.5.dist-info/METADATA
alibabacloud_companyreg20200306-2.2.5.dist-info/WHEEL
alibabacloud_companyreg20200306-2.2.5.dist-info/top_level.txt
alibabacloud_companyreg20200306-2.2.5.dist-info/RECORD
